{"cameraMode":{"drawMode":0,"name":"Shaded","section":"Shading Mode"},"sceneLighting":true,"audioPlay":false,"sceneViewState":{"m_AlwaysRefresh":false,"showFog":true,"showSkybox":true,"showFlares":true,"showImageEffects":true,"showParticleSystems":true,"showVisualEffectGraphs":true,"m_FxEnabled":true},"in2DMode":false,"pivot":{"x":0.43981313705444338,"y":1.6039619445800782,"z":-6.049678325653076},"rotation":{"x":0.31687185168266299,"y":0.6809119582176209,"z":-0.49896806478500368,"w":0.4324159622192383},"size":17.52049446105957,"orthographic":false}